{
  "2 de Octubre": "20367",
  "Abadía": "20286",
  "Agricultura": "20234",
  "Agropecuario": "20135",
  "Agua Clara": "20263",
  "Agua Nueva": "20367",
  "Aguascalientes (Barrio de San Marcos)": "20070",
  "Aguascalientes (Licenciado Jesús Terán Peredo)": "20349",
  "Zona Centro": "20000",
  "Alameda": "20180",
  "Albanta Norte": "20326",
  "Albanta Sur": "20326",
  "Alberia": "20218",
  "Alianza Ferrocarrilera": "20159",
  "Altavista": "20040",
  "Ambrosía": "20196",
  "Ampliación de Calvillito (Colonia la Herrada)": "20367",
  "Amura": "20286",
  "Andrea": "20140",
  "Anexo Palomino Dena": "20172",
  "Arellano": "20340",
  "Arroyo El Molino": "20123",
  "Australis": "20280",
  "Bajío de las Palmas": "20263",
  "Balcones de Oriente": "20196",
  "Barandales de San José": "20206",
  "Barrio de Santiago": "20115",
  "Belago Residence": "20326",
  "Palomino Dena": "20172",
  "Bona Gens": "20255",
  "Bosques del Prado Norte": "20127",
  "Bosques del Prado Sur": "20130",
  "Buenavista": "20150",
  "Buenos Aires": "20020",
  "Bugambilias": "20050",
  "Bulevares 1a Sección": "20288",
  "Bulevares 2a Sección": "20288",
  "C.T.M": "20150",
  "Cadaqués Residencial": "20118",
  "Camino Real": "20196",
  "Cantelli Residencial": "20200",
  "Canteras de San Agustín": "20218",
  "Canteras de San Javier": "20207",
  "Canteras de San José": "20208",
  "Canteras de Santa Imelda": "20218",
  "Capital City": "20207",
  "Caranday": "20286",
  "Carena": "20326",
  "Carmel": "20200",
  "Cartagena": "20126",
  "Casa Blanca": "20297",
  "Residencial Casa Sólida": "20280",
  "Cedrela": "20328",
  "Ceiba": "20218",
  "Central de Abastos": "20280",
  "CERESO (Varones y Mujeres)": "20393",
  "Del Carmen": "20050",
  "Del Trabajo": "20180",
  "Dolores": "20347",
  "Ejido Las Cumbres": "20175",
  "Ejido Ojocaliente": "20198",
  "El Caminero": "20270",
  "El Cedazo": "20263",
  "El Cobano": "20150",
  "El Dorado 1a Sección": "20235",
  "El Dorado 2a Sección": "20235",
  "El Edén": "20219",
  "Barrio del Encino": "20240",
  "El Llanito": "20240",
  "El Maguey": "20170",
  "El Niágara": "20372",
  "El Plateado": "20137",
  "El Puertecito": "20126",
  "Fátima": "20130",
  "Fidel Velázquez": "20199",
  "Francisco Guel Jimenez": "20160",
  "Francisco Villa": "20218",
  "Fuentes del Lago": "20200",
  "Fundadores": "20299",
  "Galerías": "20124",
  "Gremial": "20030",
  "Guadalupe Peralta": "20059",
  "Mangata": "20286",
  "Martínez Domínguez": "20280",
  "Matamoros": "20389",
  "México": "20270",
  "Mirador de las Culturas": "20174",
  "Miravalle": "20040",
  "Misión de Santa Lucia": "20298",
  "Misión del Campanario": "20118",
  "Modelo": "20080",
  "Moderno": "20060",
  "Montebello de la Stanza": "20126",
  "Morelos I": "20298",
  "Morelos 2a Sección": "20298",
  "Morelos Infonavit": "20264",
  "Municipio Libre": "20199",
    "Natura": "20126",
  "Nazario Ortíz Garza": "20170",
  "Norias de Ojocaliente": "20367",
  "Norias de Paso Hondo": "20384",
  "Nueva Rinconada": "20130",
  "Obraje": "20230",
  "Ojocaliente": "20196",
  "Ojocaliente INEGI": "20196",
  "Ojocaliente Fovissste III": "20256",
  "Olinda": "20200",
  "Olivares Santana": "20010",
  "Panorama": "20040",
  "Parras": "20157",
  "Pirámides": "20299",
  "Pozo Bravo Norte": "20126",
  "Primavera": "20299",
  "Progreso": "20299",
  "Rancho Santa Mónica": "20286",
  "Real del Sol": "20196",
  "Reencuentro": "20299",
  "Residencial Altaria": "20124",
  "Residencial El Encino": "20240",
  "Residencial del Valle I": "20080",
  "Residencial del Valle II": "20089",
  "Residencial Guadalupe": "20040",
  "Residencial Hacienda San Martín": "20298",
  "Residencial Las Quintas": "20329",
  "Salto de Ojocaliente": "20263",
  "San Cayetano": "20010",
  "San Francisco del Arenal": "20280",
  "San Gerardo": "20342",
  "San Ignacio I": "20326",
  "San José del Arenal": "20130",
  "San Marcos": "20070",
  "San Martín de la Cantera": "20218",
  "Santa Anita": "20218",
  "Santa Elena": "20174",
  "Santa Mónica": "20286",
  "Solidaridad 1a Sección": "20299",
  "Solidaridad 3a Sección": "20299",
  "Valle de los Cactus": "20196",
  "Valle Real": "20118",
  "Valtica": "20150",
  "Versalles 2a Sección": "20285",
  "Vicente Guerrero": "20286",
  "Villa Bonaterra": "20296",
  "Villa Loma Dorada": "20126",
  "Villa Montaña": "20126",
  "Villa Sur": "20296",
  "Viñedos del Sur": "20298",
  "Viñedos de San Felipe": "20310",
  "Vistas del Sol": "20264",
  "Vistas del Sur": "20284",
  "Vistas del Valle": "20174",
  "Vivienda Popular": "20220",
  "Zona Militar": "20170"
}
